options
xcpengine_docker
xcpengine_singularity
