Metadata-Version: 1.2
Name: xcpengine-container
Version: 1.0.1
Summary: xcpEngine is a tool for denoising fMRI data and calulating
Home-page: https://github.com/pennbbl/xcpEngine
Author: 
Author-email: 
Maintainer: 
Maintainer-email: 
License: 3-clause BSD
Platform: UNKNOWN
Classifier: Development Status :: 3 - Alpha
Classifier: Intended Audience :: Science/Research
Classifier: License :: OSI Approved :: BSD License
Classifier: Programming Language :: Python :: 3.6
